LICENSE
MANIFEST.in
README.rst
setup.cfg
setup.py
django_oscar_zarinpal_gateway/__init__.py
django_oscar_zarinpal_gateway/settings.py
django_oscar_zarinpal_gateway.egg-info/PKG-INFO
django_oscar_zarinpal_gateway.egg-info/SOURCES.txt
django_oscar_zarinpal_gateway.egg-info/dependency_links.txt
django_oscar_zarinpal_gateway.egg-info/requires.txt
django_oscar_zarinpal_gateway.egg-info/top_level.txt
django_oscar_zarinpal_gateway/checkout/__init__.py
django_oscar_zarinpal_gateway/checkout/admin.py
django_oscar_zarinpal_gateway/checkout/apps.py
django_oscar_zarinpal_gateway/checkout/bridge.py
django_oscar_zarinpal_gateway/checkout/decorators.py
django_oscar_zarinpal_gateway/checkout/forms.py
django_oscar_zarinpal_gateway/checkout/gateway.py
django_oscar_zarinpal_gateway/checkout/models.py
django_oscar_zarinpal_gateway/checkout/views.py
django_oscar_zarinpal_gateway/checkout/migrations/0001_initial.py
django_oscar_zarinpal_gateway/checkout/migrations/0002_rename_total_incl_tax_zarrinpaytransaction_amount.py
django_oscar_zarinpal_gateway/checkout/migrations/0003_rename_amount_zarrinpaytransaction_total_incl_tax.py
django_oscar_zarinpal_gateway/checkout/migrations/0004_auto_20220309_1703.py
django_oscar_zarinpal_gateway/checkout/migrations/0005_alter_zarrinpaytransaction_pay_type.py
django_oscar_zarinpal_gateway/checkout/migrations/0006_auto_20220309_1852.py
django_oscar_zarinpal_gateway/checkout/migrations/0007_auto_20220309_1901.py
django_oscar_zarinpal_gateway/checkout/migrations/0008_auto_20220311_1248.py
django_oscar_zarinpal_gateway/checkout/migrations/0009_alter_zarrinpaytransaction_shipping_address.py
django_oscar_zarinpal_gateway/checkout/migrations/0010_alter_zarrinpaytransaction_shipping_address.py
django_oscar_zarinpal_gateway/checkout/migrations/0011_alter_zarrinpaytransaction_shipping_address.py
django_oscar_zarinpal_gateway/checkout/migrations/0012_remove_zarrinpaytransaction_shipping_address.py
django_oscar_zarinpal_gateway/checkout/migrations/0013_auto_20220312_0537.py
django_oscar_zarinpal_gateway/checkout/migrations/0014_zarrinpaytransaction_shipping_address.py
django_oscar_zarinpal_gateway/checkout/migrations/__init__.py
django_oscar_zarinpal_gateway/checkout/templates/checkout/call_back_result.html
